lindera_py-0.45.0.dist-info/METADATA
lindera_py-0.45.0.dist-info/WHEEL
lindera_py/__init__.py
lindera_py/lindera_py.pypy311-pp73-aarch64-linux-gnu.so
lindera_py-0.45.0.dist-info/RECORD
