Metadata-Version: 2.4
Name: lindera-py
Version: 0.45.0
Summary: Python binding for Lindera.
Keywords: morphological,analysis,library,python
Home-Page: https://github.com/lindera-morphology/lindera-py
License: MIT
Project-URL: Source Code, https://github.com/lindera-morphology/lindera-py
